.gitignore
MANIFEST.in
README.rst
setup.py
collective/__init__.py
collective.uploadify.egg-info/PKG-INFO
collective.uploadify.egg-info/SOURCES.txt
collective.uploadify.egg-info/dependency_links.txt
collective.uploadify.egg-info/entry_points.txt
collective.uploadify.egg-info/namespace_packages.txt
collective.uploadify.egg-info/not-zip-safe
collective.uploadify.egg-info/requires.txt
collective.uploadify.egg-info/top_level.txt
collective/uploadify/__init__.py
collective/uploadify/configure.zcml
collective/uploadify/browser/__init__.py
collective/uploadify/browser/adapters.py
collective/uploadify/browser/atct.py
collective/uploadify/browser/cancel.png
collective/uploadify/browser/configure.zcml
collective/uploadify/browser/dexterity.py
collective/uploadify/browser/interfaces.py
collective/uploadify/browser/jquery.uploadify.js
collective/uploadify/browser/swfobject.js
collective/uploadify/browser/upload.pt
collective/uploadify/browser/upload.py
collective/uploadify/browser/uploader.swf
collective/uploadify/browser/uploadify.css
collective/uploadify/browser/utility.py
collective/uploadify/locales/collective.uploadify.pot
collective/uploadify/locales/da/LC_MESSAGES/collective.uploadify.po
collective/uploadify/locales/de/LC_MESSAGES/collective.uploadify.po
collective/uploadify/locales/es/LC_MESSAGES/collective.uploadify.po
collective/uploadify/locales/eu/LC_MESSAGES/collective.uploadify.po
collective/uploadify/locales/it/LC_MESSAGES/collective.uploadify.po
collective/uploadify/locales/nl/LC_MESSAGES/collective.uploadify.po
collective/uploadify/locales/zh_CN/LC_MESSAGES/collective.uploadify.po
collective/uploadify/locales/zh_TW/LC_MESSAGES/collective.uploadify.po
collective/uploadify/profiles/default/actions.xml
collective/uploadify/profiles/default/metadata.xml
collective/uploadify/tests/__init__.py
collective/uploadify/tests/base.py
collective/uploadify/tests/test_setup.py
collective/uploadify/tests/test_views.py
docs/CONTRIBUTORS.txt
docs/HISTORY.txt
docs/INSTALL.txt
docs/LICENSE.GPL
docs/LICENSE.txt