Metadata-Version: 1.1
Name: collective.uploadify
Version: 1.2
Summary: Multi File Upload for Plone
Home-page: https://github.com/collective/collective.uploadify
Author: Ramon Bartl
Author-email: rb@nexiles.de
License: GPL
Platform: UNKNOWN
Classifier: Framework :: Plone
Classifier: Programming Language :: Python
Classifier: Topic :: Software Development :: Libraries :: Python Modules
